vibium/__init__.py
vibium/browser.py
vibium/browser_sync.py
vibium/cli.py
vibium/clicker.py
vibium/client.py
vibium/element.py
vibium/vibe.py
vibium-0.1.4.dist-info/METADATA
vibium-0.1.4.dist-info/WHEEL
vibium-0.1.4.dist-info/entry_points.txt
vibium-0.1.4.dist-info/licenses/LICENSE
vibium-0.1.4.dist-info/licenses/NOTICE
vibium-0.1.4.dist-info/RECORD
