Metadata-Version: 2.4
Name: vibium
Version: 0.1.4
Summary: Browser automation for AI agents and humans
Project-URL: Homepage, https://vibium.com
Project-URL: Repository, https://github.com/VibiumDev/vibium
Project-URL: Issues, https://github.com/VibiumDev/vibium/issues
Author-email: Jason Huggins <hugs@vibium.com>
License-Expression: Apache-2.0
License-File: LICENSE
License-File: NOTICE
Requires-Python: >=3.9
Requires-Dist: vibium-darwin-arm64>=0.1.4; sys_platform == 'darwin' and platform_machine == 'arm64'
Requires-Dist: vibium-darwin-x64>=0.1.4; sys_platform == 'darwin' and platform_machine == 'x86_64'
Requires-Dist: vibium-linux-arm64>=0.1.4; sys_platform == 'linux' and platform_machine == 'aarch64'
Requires-Dist: vibium-linux-x64>=0.1.4; sys_platform == 'linux' and platform_machine == 'x86_64'
Requires-Dist: vibium-win32-x64>=0.1.4; sys_platform == 'win32' and platform_machine == 'AMD64'
Requires-Dist: websockets>=14.2
